wicafe/__init__.py
wicafe/__main__.py
wicafe-0.1.0.dist-info/LICENSE
wicafe-0.1.0.dist-info/METADATA
wicafe-0.1.0.dist-info/WHEEL
wicafe-0.1.0.dist-info/entry_points.txt
wicafe-0.1.0.dist-info/top_level.txt
wicafe-0.1.0.dist-info/RECORD
