Metadata-Version: 2.1
Name: wicafe
Version: 0.1.0
Summary: Automatic login utility of free Wi-Fi captive portals
Home-page: UNKNOWN
Author: puhitaku
Author-email: puhitaku@gmail.com
License: MIT
Platform: UNKNOWN
Classifier: Development Status :: 4 - Beta
Classifier: Programming Language :: Python :: 3.7
Classifier: Programming Language :: Python :: 3.8
Classifier: Programming Language :: Python :: 3.9
Classifier: Programming Language :: Python :: 3.10
Requires-Python: >=3.7
License-File: LICENSE
Requires-Dist: requests
Provides-Extra: dev
Requires-Dist: black (>=21.12b0) ; extra == 'dev'
Requires-Dist: flake8 (>=4.0.1) ; extra == 'dev'
Requires-Dist: isort (>=5.10.1) ; extra == 'dev'
Requires-Dist: mypy (>=0.931) ; extra == 'dev'
Requires-Dist: types-requests (>=2.27.7) ; extra == 'dev'
Requires-Dist: types-setuptools (>=57.4.7) ; extra == 'dev'
